esch/__init__.py
esch/data.py
esch/edge.py
esch/grid.py
esch/mesh.py
esch/plot.py
esch/ring.py
esch/util.py
esch-1.1.0.dist-info/LICENSE
esch-1.1.0.dist-info/METADATA
esch-1.1.0.dist-info/WHEEL
esch-1.1.0.dist-info/RECORD
